ctm/__init__.py
ctm/config.py
ctm/data.py
ctm/infer.py
ctm/infer.sh
ctm/model.py
ctm/run.sh
ctm/train.py
ctm/utils.py
scripts/__init__.py
scripts/export_topics.py
ctm_pytorch_advi-0.1.3.dist-info/METADATA
ctm_pytorch_advi-0.1.3.dist-info/WHEEL
ctm_pytorch_advi-0.1.3.dist-info/entry_points.txt
ctm_pytorch_advi-0.1.3.dist-info/RECORD
