Metadata-Version: 2.4
Name: ctm-pytorch-advi
Version: 0.1.3
Summary: Correlated Topic Model (CTM) with ADVI in PyTorch: training, inference, and utilities
License: MIT
Requires-Python: >=3.10
Requires-Dist: matplotlib>=3.10.5
Requires-Dist: numpy>=2.2.6
Requires-Dist: rich>=14.1.0
Requires-Dist: scikit-learn>=1.7.1
Requires-Dist: scipy>=1.15.3
Requires-Dist: spacy>=3.7.5
Requires-Dist: tensorboard>=2.16.2
Requires-Dist: torch>=2.8.0
Requires-Dist: tqdm>=4.67.1
Requires-Dist: tyro>=0.9.27
